logtron_aws/__init__.py
logtron_aws/autodiscover.py
logtron_aws/cloudwatch.py
logtron_aws/context.py
logtron_aws/util/__init__.py
logtron_aws/util/path.py
logtron_aws-0.1.20.dist-info/LICENSE
logtron_aws-0.1.20.dist-info/WHEEL
logtron_aws-0.1.20.dist-info/METADATA
logtron_aws-0.1.20.dist-info/RECORD
